LICENSE
Pipfile
Pipfile.lock
README.md
setup.py
sashimi/__init__.py
sashimi/cli.py
sashimi/plot.py
sashimi/plot_func.py
sashimi/plot_tests.py
sashimi.py.egg-info/PKG-INFO
sashimi.py.egg-info/SOURCES.txt
sashimi.py.egg-info/dependency_links.txt
sashimi.py.egg-info/entry_points.txt
sashimi.py.egg-info/not-zip-safe
sashimi.py.egg-info/requires.txt
sashimi.py.egg-info/top_level.txt
sashimi/anno/AxLabel.py
sashimi/anno/__init__.py
sashimi/anno/theme.py
sashimi/base/CoordinateMap.py
sashimi/base/GenomicLoci.py
sashimi/base/Junction.py
sashimi/base/Protein.py
sashimi/base/ReadDepth.py
sashimi/base/Readder.py
sashimi/base/Stroke.py
sashimi/base/Transcript.py
sashimi/base/__init__.py
sashimi/base/pyUniprot.py
sashimi/conf/DomainSetting.py
sashimi/conf/__init__.py
sashimi/conf/config.py
sashimi/conf/drawing.py
sashimi/file/ATAC.py
sashimi/file/Bam.py
sashimi/file/BedGraph.py
sashimi/file/Bigwig.py
sashimi/file/Depth.py
sashimi/file/Fasta.py
sashimi/file/File.py
sashimi/file/HiCMatrixTrack.py
sashimi/file/Junction.py
sashimi/file/Motif.py
sashimi/file/ReadSegments.py
sashimi/file/Reference.py
sashimi/file/__init__.py