Metadata-Version: 2.1
Name: sashimi.py
Version: 0.1.2
Home-page: https://github.com/ygidtu/sashimi.py
Requires-Python: >=3.6
License-File: LICENSE
